ottos_expeditions/__init__.py
ottos_expeditions/lib/seed.py
ottos_expeditions/lib/synthetic.py
ottos_expeditions/lib/transform.py
ottos_expeditions/ui/cli.py
ottos_expeditions/ui/gui.py
ottos_expeditions-0.0.5.dist-info/METADATA
ottos_expeditions-0.0.5.dist-info/WHEEL
ottos_expeditions-0.0.5.dist-info/entry_points.txt
ottos_expeditions-0.0.5.dist-info/RECORD
